seastar/__about__.py
seastar/__init__.py
seastar/exceptions.py
seastar/json.py
seastar/requests.py
seastar/responses.py
seastar/routing.py
seastar/types.py
seastar/middleware/__init__.py
seastar/middleware/exceptions.py
seastar-0.4.1.dist-info/METADATA
seastar-0.4.1.dist-info/WHEEL
seastar-0.4.1.dist-info/licenses/LICENSE.txt
seastar-0.4.1.dist-info/RECORD
