Metadata-Version: 2.1
Name: seastar
Version: 0.4.1
Summary: A FaaS (Function as a service) framework for Digital Ocean Cloud Functions influenced by Starlette.
Project-URL: Documentation, https://github.com/rykroon/seastar#readme
Project-URL: Issues, https://github.com/rykroon/seastar/issues
Project-URL: Source, https://github.com/rykroon/seastar
Author-email: Ryan Kroon <rykroon.tech@gmail.com>
License-Expression: MIT
License-File: LICENSE.txt
Classifier: Development Status :: 4 - Beta
Classifier: Programming Language :: Python
Classifier: Programming Language :: Python :: 3.9
Classifier: Programming Language :: Python :: 3.10
Classifier: Programming Language :: Python :: 3.11
Classifier: Programming Language :: Python :: Implementation :: CPython
Requires-Python: >=3.9
Requires-Dist: starlette==0.31.*
Requires-Dist: typing-extensions==4.*
